deep_breath_cli/__init__.py
deep_breath_cli/breath.py
deep_breath_cli/presets.py
deep_breath_cli/stats.py
deep_breath_cli-1.1.3.dist-info/METADATA
deep_breath_cli-1.1.3.dist-info/WHEEL
deep_breath_cli-1.1.3.dist-info/entry_points.txt
deep_breath_cli-1.1.3.dist-info/licenses/LICENSE
deep_breath_cli-1.1.3.dist-info/RECORD
