Metadata-Version: 2.4
Name: deep-breath-cli
Version: 1.1.3
Summary: A command-line tool designed to help you relax from your terminal.
Project-URL: Homepage, https://github.com/weart99/deep-breath-cli
Project-URL: Repository, https://github.com/weart99/deep-breath-cli
Project-URL: Issues, https://github.com/weart99/deep-breath-cli/issues
Author-email: Arthur Parmentier <arthurparmentier99@gmail.com>
License: MIT
License-File: LICENSE
Keywords: breathing,cli,meditation,relaxation,stress,terminal,wellness
Classifier: Development Status :: 4 - Beta
Classifier: Environment :: Console
Classifier: Intended Audience :: End Users/Desktop
Classifier: License :: OSI Approved :: MIT License
Classifier: Programming Language :: Python :: 3
Classifier: Programming Language :: Python :: 3.12
Classifier: Programming Language :: Python :: 3.13
Classifier: Topic :: Utilities
Requires-Python: >=3.12
Requires-Dist: plotext>=5.3.2
Requires-Dist: rich>=14.1.0
Requires-Dist: typer>=0.16.0
Provides-Extra: dev
Requires-Dist: pytest-cov>=6.2.1; extra == 'dev'
Requires-Dist: pytest>=8.4.1; extra == 'dev'
Requires-Dist: ruff>=0.12.4; extra == 'dev'
